{
  "paragraph": [
    {
      "paragraph_txt": "석가모니의 출생은 아직까지도 잘 밝혀지지 않았고 기원전 6세기경에 태어났다고 추측되고있다.#@문장구분# 히말라야의 작은나라에서 태어난 석가모니는 왕가출신으로 비사밀다를 스승으로 두고 여러 학문을 배우고 외삼촌에게서 무술을 배우면서 자랐다고 한다. #@문장구분#이후 12세가 되던해에 정식 후계자로 책정되었는데 당시 석가모니는 신분의 차이와 먹이사슬에대해 고민하면서 많은 생각을 하게되었다고 한다.#@문장구분# 이후 그런 고민을 견딜수가 없어 말을 타고 궁을 자주 빠져나가 숲에서 고민을 했다고 한다.#@문장구분# 이후 왕이나 신하들은 석가모니의 출타를 막고 왕으로 무사히 즉위시키려고 하지만 석가모니는 결국엔 출가를 하게된다.#@문장구분# 석가모니는 출가 이후에 고된 삶과 직면하게된다. #@문장구분#하지만 그런 삶에서도 본인의 고민에대한 해답을 얻을수 없어 스승을 찾게된다. #@문장구분#이후 스승을 얻고 고행을 함에도 깨달음을 얻지 못하고 여러가지 방법을 시도해보게된다.#@문장구분# 이후 고행림으로 가서 다시 고행에 들어가게된다.#@문장구분# 고행림에서 6년간 인간으로써 버티기 힘들정도로 고행을 했다고 한다. #@문장구분#하지만 이런 고행에도 깨달음을 얻지 못했으나  유혹을 이겨내고 결국 깨달음을 얻게되었다고 전해진다. #@문장구분#그리고 그가 깨달은것을 전파해 혹독한 삶으로 고통받는 원인을 알려주고 해결책을 제시해주어 여러 사람들을 정신적으로 편안하게 해주었고 이런점이 석가모니의 사상이 위대한 이유중 하나이다.#@문장구분# 나도 석가모니처럼 깨달음을 얻어 많은 사람들에게 좋은 영향을 주는 사람이 되고싶다.#@문장구분#",
      "paragraph_len": 971,
      "paragraph_id": "001"
    }
  ],
  "score": {
    "paragraph_score": [
      {
        "paragraph_scoreT": [
          2.7142856,
          2.4285715,
          2
        ],
        "paragraph_scoreT_detail": {
          "paragraph_scoreT_exp": [
            [
              2,
              3,
              3
            ],
            [
              2,
              3,
              2
            ],
            [
              2,
              2,
              2
            ]
          ]
        },
        "paragraph_scoreT_avg": 2.3809524,
        "paragraph_id": "001"
      }
    ],
    "essay_scoreT": [
      28.857143,
      25.103174,
      22
    ],
    "essay_scoreT_avg": 25.320107,
    "essay_scoreT_detail": {
      "essay_scoreT_org": [
        [
          3,
          3,
          3,
          3
        ],
        [
          3,
          2,
          2,
          3
        ],
        [
          2,
          2,
          2,
          2
        ]
      ],
      "essay_scoreT_cont": [
        [
          3,
          3,
          0,
          3
        ],
        [
          3,
          2,
          0,
          3
        ],
        [
          3,
          2,
          0,
          2
        ]
      ],
      "essay_scoreT_exp": [
        [
          2,
          3,
          3
        ],
        [
          2,
          3,
          2
        ],
        [
          2,
          2,
          2
        ]
      ]
    }
  },
  "student": {
    "date": "2021.11.01",
    "student_educated": true,
    "student_grade": "고등_3학년",
    "location": "063",
    "student_grade_group": "고등",
    "student_reading": 3
  },
  "rubric": {
    "essay_grade": "고등_3학년",
    "organization_weight": {
      "org_paragraph": 3,
      "org": 2,
      "org_essay": 3,
      "org_coherence": 2,
      "org_quantity": 1
    },
    "essay_type": "설명글",
    "content_weight": {
      "con_clearance": 4,
      "con_novelty": 3,
      "con": 4,
      "con_prompt": 0,
      "con_description": 1
    },
    "essay_main_subject": "나의 위인전",
    "expression_weight": {
      "exp_style": 2,
      "exp_grammar": 2,
      "exp_vocab": 3,
      "exp": 4
    }
  },
  "correction": [],
  "info": {
    "essay_id": "ESSAY_40027",
    "essay_prompt": " 요즘은 책을 통해서뿐만 아니라 유튜브, 강의와 같이 다양한 매체를 통해 자신만의 롤모델을 찾을 수 있습니다.\n\n 여러분도 자신만의 롤모델이 있을 것 같은데요. 자신의 롤모델인 인물처럼 되었다고 생각하고 나만의 위인전을 작성해보세요. 본인이 그 사람이 되었다고 생각하고 작성해도 좋고, 제 3자의 입장에서 바라보는 형식으로 작성해도 좋아요.\n\n 나의 롤모델은 목표를 이루기 위해 어떤 노력을 했을지, 어떤 행운이 있었을지, 목표를 이루고 난 다음에 어떤 기분이 들었을지 마음 껏 상상해보시고 작성해주세요.",
    "essay_type": "글짓기",
    "essay_level": "2",
    "essay_len": 711,
    "essay_main_subject": "나의 위인전"
  }
}