{
  "paragraph": [
    {
      "paragraph_txt": "내가 생각하는 미래 도시의 모습은 높은 건물이 많이 있고, 하늘을 나는 자동차가 있으며 모두 수소 자동차, 전기 자동차다.#@문장구분# 그리고 하이퍼 루프가 있다.#@문장구분# 또 첨단 기술이 발전하여 질병이 없다.#@문장구분# 그리고 거리에는 로봇이 있으며, 환경오염이 안 된 도시이고, 건물들마다 크고 화려한 전광판이 있다.#@문장구분# 도 우주선을 타고, 화성이나 다른 은하에도 갈 수 있고 시간여행이 가능하여 과거나 100년 미래도 갈 수 있다.#@문장구분# 건물들은 모두 20층이 넘는다.#@문장구분# 또 인공지능이 있다. #@문장구분#그리고 교과서로 안 배우고 디지털이나 TV로 배운다.#@문장구분# 또 로봇이 많지는 않고 조금 있다.#@문장구분# 이유는 로봇이 많으면 일자리가 없기 때문이다. #@문장구분#그리고 또 로봇은 편하지만 잘못하면 로봇이 반란을 일으킬 수 있었기 때문이다.#@문장구분# 그리고 드론을 이용한 직업이 많을 것 같다.#@문장구분# 또 우주선으로 가기 때문에 탐사선이 없어지지 않을 것 같다.#@문장구분# 이상으로 내가 생각하는 미래도시의 모습이었다.#@문장구분#",
      "paragraph_len": 740,
      "paragraph_id": "001"
    }
  ],
  "score": {
    "paragraph_score": [
      {
        "paragraph_scoreT": [
          2.5,
          3,
          3
        ],
        "paragraph_scoreT_detail": {
          "paragraph_scoreT_exp": [
            [
              3,
              2,
              0
            ],
            [
              3,
              3,
              0
            ],
            [
              3,
              3,
              0
            ]
          ]
        },
        "paragraph_scoreT_avg": 2.8333333,
        "paragraph_id": "001"
      }
    ],
    "essay_scoreT": [
      26.5,
      28.4,
      30
    ],
    "essay_scoreT_avg": 28.300001,
    "essay_scoreT_detail": {
      "essay_scoreT_org": [
        [
          2,
          3,
          3,
          2
        ],
        [
          3,
          3,
          3,
          3
        ],
        [
          3,
          3,
          3,
          3
        ]
      ],
      "essay_scoreT_cont": [
        [
          3,
          3,
          0,
          3
        ],
        [
          3,
          2,
          0,
          3
        ],
        [
          3,
          3,
          0,
          3
        ]
      ],
      "essay_scoreT_exp": [
        [
          3,
          2,
          0
        ],
        [
          3,
          3,
          0
        ],
        [
          3,
          3,
          0
        ]
      ]
    }
  },
  "student": {
    "date": "2021.08.31",
    "student_educated": true,
    "student_grade": "중등_1학년",
    "location": "031",
    "student_grade_group": "중등",
    "student_reading": 1
  },
  "rubric": {
    "essay_grade": "중등_1학년",
    "organization_weight": {
      "org_paragraph": 1,
      "org": 2,
      "org_essay": 5,
      "org_coherence": 1,
      "org_quantity": 1
    },
    "essay_type": "글짓기",
    "content_weight": {
      "con_clearance": 4,
      "con_novelty": 4,
      "con": 4,
      "con_prompt": 0,
      "con_description": 2
    },
    "essay_main_subject": "미래 도시에 대한 본인의 생각",
    "expression_weight": {
      "exp_style": 0,
      "exp_grammar": 3,
      "exp_vocab": 3,
      "exp": 4
    }
  },
  "correction": [],
  "info": {
    "essay_id": "ESSAY_53471",
    "essay_prompt": " 미래의 도시는 어떤 모습일까요?\n\n 기술의 발전으로 인해 자동차가 하늘을 날아다니고 사람들은 로봇과 자연스럽게 대화하며 지낼까요?\n\n 아니면 더 이상의 환경 파괴를 하지 말자고 결정되어 기계를 줄이고 숲과 동물들과 함께 어울려 살아가게 될까요?\n\n 외계인과 소통하는 세계가 되어있을 수도 있겠네요!\n\n 자신이 생각하는 미래 도시의 이름을 지어주세요. 그리고 미래 도시의 모습을 상상하여 자유롭게 작성해주세요. 그렇게 생각한 이유를 작성해주면 더욱더 좋을 것 같아요.",
    "essay_type": "글짓기",
    "essay_level": "2",
    "essay_len": 461,
    "essay_main_subject": "미래 도시에 대한 본인의 생각"
  }
}