{
  "paragraph": [
    {
      "paragraph_txt": "나는 일주일동안 바다거북으로 변할것이다.#@문장구분# 바다거북이 되어 바다를 탐험하면서 무엇이 있나 찾아보고 쓰레기를 먹을려하는 물고기들을 못먹게 했다.#@문장구분# 그리고 쓰레기를 한곳에 치워뒀다. #@문장구분#그리고 바다 깊은곳으로 내려갔다. #@문장구분#깊은곳에는 아귀등등이 있었다.#@문장구분# 깊은곳에는 신기한 생물들이 많았다. #@문장구분#다시 위로 올라와 위에는 무엇이 있나 찾아보았다. #@문장구분#위에는 쓰레기가 많았따. #@문장구분#살짝 밑으로 가니 여러해양생물들이 많았다.#@문장구분# 계속 돌아다니다 보니 고래도 보았다.#@문장구분# 고래를 바로 앞에서보니까 되게 신기했다#@문장구분# 그리고 일주일이 지나 다시 사람으로 변했다.#@문장구분#",
      "paragraph_len": 527,
      "paragraph_id": "001"
    }
  ],
  "score": {
    "paragraph_score": [
      {
        "paragraph_scoreT": [
          2,
          2,
          2.5
        ],
        "paragraph_scoreT_detail": {
          "paragraph_scoreT_exp": [
            [
              2,
              2,
              0
            ],
            [
              2,
              2,
              0
            ],
            [
              2,
              3,
              0
            ]
          ]
        },
        "paragraph_scoreT_avg": 2.1666667,
        "paragraph_id": "001"
      }
    ],
    "essay_scoreT": [
      18.15,
      21.85,
      27.75
    ],
    "essay_scoreT_avg": 22.583334,
    "essay_scoreT_detail": {
      "essay_scoreT_org": [
        [
          2,
          2,
          2,
          1
        ],
        [
          2,
          2,
          2,
          3
        ],
        [
          3,
          3,
          3,
          2
        ]
      ],
      "essay_scoreT_cont": [
        [
          2,
          1,
          0,
          2
        ],
        [
          3,
          2,
          0,
          2
        ],
        [
          3,
          3,
          0,
          3
        ]
      ],
      "essay_scoreT_exp": [
        [
          2,
          2,
          0
        ],
        [
          2,
          2,
          0
        ],
        [
          2,
          3,
          0
        ]
      ]
    }
  },
  "student": {
    "date": "2021.10.18",
    "student_educated": true,
    "student_grade": "초등_6학년",
    "location": "042",
    "student_grade_group": "초등",
    "student_reading": 2
  },
  "rubric": {
    "essay_grade": "초등_6학년",
    "organization_weight": {
      "org_paragraph": 1,
      "org": 2,
      "org_essay": 5,
      "org_coherence": 1,
      "org_quantity": 1
    },
    "essay_type": "글짓기",
    "content_weight": {
      "con_clearance": 4,
      "con_novelty": 4,
      "con": 4,
      "con_prompt": 0,
      "con_description": 2
    },
    "essay_main_subject": "바다 생물 이야기 짓기",
    "expression_weight": {
      "exp_style": 0,
      "exp_grammar": 3,
      "exp_vocab": 3,
      "exp": 4
    }
  },
  "correction": [],
  "info": {
    "essay_id": "ESSAY_38339",
    "essay_prompt": " 바다는 지구 표면의 약 70%를 차지합니다. 그 속에는 무수한 생물이 살고 있는데 아직 밝혀지지 않은 종류도 많이 있습니다.\n\n 정말 넓고 신비로운 바다라는 곳에서 딱 일주일 동안 바다의 생물로 살아갈 기회가 주어진다면 여러분은 어떤 생물로 변신하고 싶으신가요?\n\n 원하는 생물을 정했다면 바다에서 어떤 모험을 하고 싶나요? 깊은 바다에 들어갈 수도 있고 아주 큰 고래가 되어 위험한 바다생물들을 도와줄 수도 있을 것 같아요.\n\n 관심 있는 바다 생물을 정하여 이유를 작성해주세요. 그리고 그 바다생물이 되어 바다를 모험하는 이야기를 상상하여 지어보세요.",
    "essay_type": "글짓기",
    "essay_level": "3",
    "essay_len": 287,
    "essay_main_subject": "바다 생물 이야기 짓기"
  }
}