{
  "paragraph": [
    {
      "paragraph_txt": "나도 예전에 할머니 손에서 자랐는데 맨날 밥을 해주시고 간식을 주시는게 익숙해지고 감사하다는 마음이 점점 사라져 나중에는 그냥 당연하다는 인식이 들었고, 오히려 반찬의 종류나 개수를 더 늘려 달라는 둥 더 많은 것을 요구하기 시작했다. #@문장구분#그래서 전날과 똑같은 반찬이 나오면 \"왜 이것 밖에 안했어?\"라는 소리를 했고 그 결과 할마니와의 관계가 틀어졌다.#@문장구분# 처음에는 할머니에게 잘 공감하지 못했지만, 다시 생각해보니 할머니는 정성스러운 마음으로 매일 아침 열심히 해주시는데 나는 그것의 감사함과 소중함을 까먹고 있었다.#@문장구분# 그래서 내 자신이 부끄러웠고 이 관계를 회복하기 위해 이제 밥이 나올 때 반찬 투정을 하지 않고 항상 고마운 마음으로 맛있게 먹고 감사하다고 하면서 노력해 결국 사이가 호전됐다.#@문장구분# 앞으로는 익숙함에 속지 않고 항상 고마운 마음을 지내며 살아가는게 어떨까?#@문장구분#",
      "paragraph_len": 529,
      "paragraph_id": "001"
    }
  ],
  "score": {
    "paragraph_score": [
      {
        "paragraph_scoreT": [
          2,
          2.5,
          2.8333333
        ],
        "paragraph_scoreT_detail": {
          "paragraph_scoreT_exp": [
            [
              2,
              2,
              2
            ],
            [
              2,
              3,
              2
            ],
            [
              3,
              3,
              2
            ]
          ]
        },
        "paragraph_scoreT_avg": 2.4444444,
        "paragraph_id": "001"
      }
    ],
    "essay_scoreT": [
      20.222221,
      25.166666,
      28.88889
    ],
    "essay_scoreT_avg": 24.759256,
    "essay_scoreT_detail": {
      "essay_scoreT_org": [
        [
          2,
          2,
          2,
          3
        ],
        [
          3,
          2,
          2,
          1
        ],
        [
          3,
          3,
          3,
          1
        ]
      ],
      "essay_scoreT_cont": [
        [
          2,
          2,
          0,
          2
        ],
        [
          3,
          2,
          0,
          3
        ],
        [
          3,
          3,
          0,
          3
        ]
      ],
      "essay_scoreT_exp": [
        [
          2,
          2,
          2
        ],
        [
          2,
          3,
          2
        ],
        [
          3,
          3,
          2
        ]
      ]
    }
  },
  "student": {
    "date": "2021.12.28",
    "student_educated": true,
    "student_grade": "고등_1학년",
    "location": "063",
    "student_grade_group": "고등",
    "student_reading": 2
  },
  "rubric": {
    "essay_grade": "고등_1학년",
    "organization_weight": {
      "org_paragraph": 2,
      "org": 2,
      "org_essay": 4,
      "org_coherence": 2,
      "org_quantity": 1
    },
    "essay_type": "글짓기",
    "content_weight": {
      "con_clearance": 4,
      "con_novelty": 3,
      "con": 4,
      "con_prompt": 0,
      "con_description": 1
    },
    "essay_main_subject": "소중함을 잃었던 경험",
    "expression_weight": {
      "exp_style": 1,
      "exp_grammar": 2,
      "exp_vocab": 3,
      "exp": 4
    }
  },
  "correction": [],
  "info": {
    "essay_id": "ESSAY_84169",
    "essay_prompt": " 익숙함에 속아 소중함을 잊지 말자는 명언 (Do not get fooled by something familiar and forget what is priceless.)이 있습니다.\n\n 부모님께서 매일 해주시는 아침밥이나, 너무 친해서 매일 맛있는 간식을 사주는 친구 등 처음에는 매우 감사했지만 반복되는 호의에 우리는 소중함을 잊어가기도 합니다.\n\n 작은 소중함일지라도 그 소중함을 잃게 되면 호의를 베푸는 사람 입장에서는 매우 당황스럽고 기분이 나쁠 수 있어요.\n\n 여러분은 익숙함에 속아 소중함을 잊었던 사례와 그로 인해 상대방의 기분을 나쁘게 했던 경험이 있나요? 만약 있다면 관계를 회복하기 위해 어떤 노력을 하셨나요? 본인의 경험을 작성해주세요.\n\n 만약 그런 적이 없다면 주변의 이야기나 본인에게 소중함을 주는 사람들에 관해 설명해주세요.",
    "essay_type": "글짓기",
    "essay_level": "2",
    "essay_len": 433,
    "essay_main_subject": "소중함을 잃었던 경험"
  }
}