{
  "paragraph": [
    {
      "paragraph_txt": "이순신은 1545년 인종 1년때 3월 8일 서울 건천동에서 이정의 셋째 아들로 태어났다#@문장구분# 21세가 되는 1565년 방진의 딸인 방수진과 결혼하고 1573년 29세 되는해에 훈련원 별과에 응시했다가 낙마하여 탈락했다.#@문장구분# 1576년 32세 2월 되는해에 무과에 급제하고 권지훈련원봉사로 첫 관직을 받았다#@문장구분# 12월엔 동구비 보권관으로 부임했다#@문장구분# 35세가되는해 1576년 2월에 한성 훈련원 봉사로 재직하고 10월에 충청도 병바 절도사 군관이 되어 충청도 해미 병영으로 갔다.#@문장구분# 1580년 36세가 되는해 7 월에 전라 좌수영 관내 발포 종4품 수군만호로 전근을 갔는데 서익이 불러 부당인사를 제안하나 거절했다.#@문장구분# 그로인해 서인은 이순인이 38세가 되는 1582년 1월에 군기경차관으로 와서 과거에 있었던 일에 대한 복수로 근무태만이라 거짓보고를 올려 발포 수군 만호직에서 파직되었다#@문장구분# 5월엔 훈련원 봉사로 재직 되고 42세의 나이에 아버지의 별세 소식에 벼슬을 잠시떠나 삼년상을 치르고 42세의 복직하고 42세 10월에 북병사 이일의 모함으로 백의종군 처벌이 내려지게 된다#@문장구분# 그 이후 45세의 나잉에 전라도 정읍현감이되고 47세의 나이에 전라좌도 수군절도사로 초수된다#@문장구분#이듬해인 1592년 임진왜란이 발발하고 전투마다 승리를 거두며 승승장구하다 53세의 나이인 1597년에 선조가 이순신의 파직을 명하게 된다#@문장구분# 다행히 2달만에 옥중생활을 마치고 나오고 그해 9월 16일 너무나도 유명한 명량해전에서 13척의 배로 일본군 133척과 맞서 싸워 승리했다#@문장구분# 이순신의 인생은 파란만장했다#@문장구분# 정직하고 청렴하게 살아왔지만 모함에의해 꺾이기도 했다#@문장구분#. 하지만 이순신은 조선의 백성을 위해 나라를 위해 끝까지 싸우고 결국 전투중에 전사하게 되었다.#@문장구분#\n 이순신은 현재까지도 세계적으로 유명한 해군제독으로 평가 받으며 우리나라는 이순신이 아니였다면 일본에 진작 점령 당할 수 있다#@문장구분#. 우리는 이순신에게 감사하며 살아가야 한다#@문장구분#",
      "paragraph_len": 1256,
      "paragraph_id": "001"
    }
  ],
  "score": {
    "paragraph_score": [
      {
        "paragraph_scoreT": [
          2.7142856,
          2.7142856,
          2
        ],
        "paragraph_scoreT_detail": {
          "paragraph_scoreT_exp": [
            [
              3,
              3,
              2
            ],
            [
              3,
              3,
              2
            ],
            [
              2,
              2,
              2
            ]
          ]
        },
        "paragraph_scoreT_avg": 2.4761903,
        "paragraph_id": "001"
      }
    ],
    "essay_scoreT": [
      25.968254,
      25.301586,
      24.666666
    ],
    "essay_scoreT_avg": 25.31217,
    "essay_scoreT_detail": {
      "essay_scoreT_org": [
        [
          2,
          3,
          3,
          2
        ],
        [
          2,
          2,
          3,
          2
        ],
        [
          2,
          2,
          3,
          3
        ]
      ],
      "essay_scoreT_cont": [
        [
          3,
          2,
          0,
          2
        ],
        [
          3,
          2,
          0,
          2
        ],
        [
          3,
          3,
          0,
          3
        ]
      ],
      "essay_scoreT_exp": [
        [
          3,
          3,
          2
        ],
        [
          3,
          3,
          2
        ],
        [
          2,
          2,
          2
        ]
      ]
    }
  },
  "student": {
    "date": "2021.08.30",
    "student_educated": true,
    "student_grade": "고등_3학년",
    "location": "063",
    "student_grade_group": "고등",
    "student_reading": 1
  },
  "rubric": {
    "essay_grade": "고등_3학년",
    "organization_weight": {
      "org_paragraph": 3,
      "org": 2,
      "org_essay": 3,
      "org_coherence": 2,
      "org_quantity": 1
    },
    "essay_type": "설명글",
    "content_weight": {
      "con_clearance": 4,
      "con_novelty": 3,
      "con": 4,
      "con_prompt": 0,
      "con_description": 1
    },
    "essay_main_subject": "나의 위인전",
    "expression_weight": {
      "exp_style": 2,
      "exp_grammar": 2,
      "exp_vocab": 3,
      "exp": 4
    }
  },
  "correction": [],
  "info": {
    "essay_id": "ESSAY_36677",
    "essay_prompt": " 요즘은 책을 통해서뿐만 아니라 유튜브, 강의와 같이 다양한 매체를 통해 자신만의 롤모델을 찾을 수 있습니다.\n\n 여러분도 자신만의 롤모델이 있을 것 같은데요. 자신의 롤모델인 인물처럼 되었다고 생각하고 나만의 위인전을 작성해보세요. 본인이 그 사람이 되었다고 생각하고 작성해도 좋고, 제 3자의 입장에서 바라보는 형식으로 작성해도 좋아요.\n\n 나의 롤모델은 목표를 이루기 위해 어떤 노력을 했을지, 어떤 행운이 있었을지, 목표를 이루고 난 다음에 어떤 기분이 들었을지 마음 껏 상상해보시고 작성해주세요.",
    "essay_type": "글짓기",
    "essay_level": "2",
    "essay_len": 937,
    "essay_main_subject": "나의 위인전"
  }
}