{
  "paragraph": [
    {
      "paragraph_txt": "미래 도시에는 공룡이 다시 살 것이다.#@문장구분# 미래도시 이름은 '쥬라기시티' 영화 쥬라기월드에서 참고했다. #@문장구분#쥬라기 월드에서 공룡이 살아나서 동물원처럼 공룡들을 구경하는 내용이다.#@문장구분# 미래도시에는 공룡들을 살릴 수 있을 것 같기 때문에 쥬라기 월드처럼 쥬라기 시티가 될 것 같다.#@문장구분# 기술이 발전하고 사람들이 더 똑똑해지면 공룡들이 왜 멸종되었는지도 밝혀내고 그러면 공룡들을 다시 복원도 할 수 있을 것이라고 생각한다.#@문장구분# 그래서 공룡들이 사는 곳도 따로 만들 것이다.#@문장구분# 또 공룡이 복원되면서 많은 동물들의 비밀이나 밝히지 못한 것들도 밝혀내서 동물이나 생명과학 같은 것이 크게 발전할 것이라고 생각한다.#@문장구분# 그리고 또 공룡을 사육하고 관리할 수 있는 직업, 공룡 먹이를 만드는 직업 등 공룡 덕분에 다양한  직업이 생길 것이라고 생각한다.#@문장구분#",
      "paragraph_len": 560,
      "paragraph_id": "001"
    }
  ],
  "score": {
    "paragraph_score": [
      {
        "paragraph_scoreT": [
          3,
          2.5,
          3
        ],
        "paragraph_scoreT_detail": {
          "paragraph_scoreT_exp": [
            [
              3,
              3,
              0
            ],
            [
              2,
              3,
              0
            ],
            [
              3,
              3,
              0
            ]
          ]
        },
        "paragraph_scoreT_avg": 2.8333333,
        "paragraph_id": "001"
      }
    ],
    "essay_scoreT": [
      30,
      25.9,
      30
    ],
    "essay_scoreT_avg": 28.633333,
    "essay_scoreT_detail": {
      "essay_scoreT_org": [
        [
          3,
          3,
          3,
          3
        ],
        [
          3,
          2,
          2,
          3
        ],
        [
          3,
          3,
          3,
          3
        ]
      ],
      "essay_scoreT_cont": [
        [
          3,
          3,
          0,
          3
        ],
        [
          3,
          2,
          0,
          3
        ],
        [
          3,
          3,
          0,
          3
        ]
      ],
      "essay_scoreT_exp": [
        [
          3,
          3,
          0
        ],
        [
          2,
          3,
          0
        ],
        [
          3,
          3,
          0
        ]
      ]
    }
  },
  "student": {
    "date": "2021.12.04",
    "student_educated": true,
    "student_grade": "중등_1학년",
    "location": "054",
    "student_grade_group": "중등",
    "student_reading": 2
  },
  "rubric": {
    "essay_grade": "중등_1학년",
    "organization_weight": {
      "org_paragraph": 1,
      "org": 2,
      "org_essay": 5,
      "org_coherence": 1,
      "org_quantity": 1
    },
    "essay_type": "글짓기",
    "content_weight": {
      "con_clearance": 4,
      "con_novelty": 4,
      "con": 4,
      "con_prompt": 0,
      "con_description": 2
    },
    "essay_main_subject": "미래 도시에 대한 본인의 생각",
    "expression_weight": {
      "exp_style": 0,
      "exp_grammar": 3,
      "exp_vocab": 3,
      "exp": 4
    }
  },
  "correction": [],
  "info": {
    "essay_id": "ESSAY_71624",
    "essay_prompt": " 미래의 도시는 어떤 모습일까요?\n\n 기술의 발전으로 인해 자동차가 하늘을 날아다니고 사람들은 로봇과 자연스럽게 대화하며 지낼까요?\n\n 아니면 더 이상의 환경 파괴를 하지 말자고 결정되어 기계를 줄이고 숲과 동물들과 함께 어울려 살아가게 될까요?\n\n 외계인과 소통하는 세계가 되어있을 수도 있겠네요!\n\n 자신이 생각하는 미래 도시의 이름을 지어주세요. 그리고 미래 도시의 모습을 상상하여 자유롭게 작성해주세요. 그렇게 생각한 이유를 작성해주면 더욱더 좋을 것 같아요.",
    "essay_type": "글짓기",
    "essay_level": "2",
    "essay_len": 401,
    "essay_main_subject": "미래 도시에 대한 본인의 생각"
  }
}