{
  "paragraph": [
    {
      "paragraph_txt": "내가 생각하는 우리가 사는 미래 도시는 인체 실험의 대가로 많은 사람들이 고통받고 있을 것이며 그로 인해 인권단체와 과학단체의 팽팽한 기싸움이 있을 것이다.#@문장구분# 그러던 와중에 인체 실험에 성공한 사례가 나타나 진화한 인간을 우리는 처음. 발견할 것이고 고도로 진화한 인간은 우리 같은 평범한 인간과는 다르게 높은 iq와 강화된 신체 능력을 가질 수도 있다.#@문장구분# 아무런 장비 없이 물속 깊은 곳까지 수영할 수 있고 또 건물과 건물을 점프하며 날아다닐 수 있는 능력까지 있다.#@문장구분# 또한 수킬로미터 밖에 있는 간판의 글씨까지 볼 수 있는 시력도 가지고 있을 것이고 마치 슈퍼맨과 같은 능력을 자랑하는 진화한 인간의 처음 생겨날 것이라고 생각한다.#@문장구분# 분명 이것은 인간의 가치관에 위배되는것이나 우리 인간들이 한번은 거쳐야할 진화가 아닐까 생각한다.#@문장구분#",
      "paragraph_len": 507,
      "paragraph_id": "001"
    }
  ],
  "score": {
    "paragraph_score": [
      {
        "paragraph_scoreT": [
          2.5,
          3,
          2.5
        ],
        "paragraph_scoreT_detail": {
          "paragraph_scoreT_exp": [
            [
              2,
              3,
              0
            ],
            [
              3,
              3,
              0
            ],
            [
              3,
              2,
              0
            ]
          ]
        },
        "paragraph_scoreT_avg": 2.6666667,
        "paragraph_id": "001"
      }
    ],
    "essay_scoreT": [
      24.9,
      28.4,
      20.5
    ],
    "essay_scoreT_avg": 24.6,
    "essay_scoreT_detail": {
      "essay_scoreT_org": [
        [
          2,
          3,
          3,
          2
        ],
        [
          3,
          3,
          3,
          3
        ],
        [
          1,
          1,
          1,
          3
        ]
      ],
      "essay_scoreT_cont": [
        [
          2,
          3,
          0,
          3
        ],
        [
          2,
          3,
          0,
          3
        ],
        [
          2,
          2,
          0,
          2
        ]
      ],
      "essay_scoreT_exp": [
        [
          2,
          3,
          0
        ],
        [
          3,
          3,
          0
        ],
        [
          3,
          2,
          0
        ]
      ]
    }
  },
  "student": {
    "date": "2021.11.23",
    "student_educated": true,
    "student_grade": "중등_1학년",
    "location": "054",
    "student_grade_group": "중등",
    "student_reading": 1
  },
  "rubric": {
    "essay_grade": "중등_1학년",
    "organization_weight": {
      "org_paragraph": 1,
      "org": 2,
      "org_essay": 5,
      "org_coherence": 1,
      "org_quantity": 1
    },
    "essay_type": "글짓기",
    "content_weight": {
      "con_clearance": 4,
      "con_novelty": 4,
      "con": 4,
      "con_prompt": 0,
      "con_description": 2
    },
    "essay_main_subject": "미래 도시에 대한 본인의 생각",
    "expression_weight": {
      "exp_style": 0,
      "exp_grammar": 3,
      "exp_vocab": 3,
      "exp": 4
    }
  },
  "correction": [],
  "info": {
    "essay_id": "ESSAY_56320",
    "essay_prompt": " 미래의 도시는 어떤 모습일까요?\n\n 기술의 발전으로 인해 자동차가 하늘을 날아다니고 사람들은 로봇과 자연스럽게 대화하며 지낼까요?\n\n 아니면 더 이상의 환경 파괴를 하지 말자고 결정되어 기계를 줄이고 숲과 동물들과 함께 어울려 살아가게 될까요?\n\n 외계인과 소통하는 세계가 되어있을 수도 있겠네요!\n\n 자신이 생각하는 미래 도시의 이름을 지어주세요. 그리고 미래 도시의 모습을 상상하여 자유롭게 작성해주세요. 그렇게 생각한 이유를 작성해주면 더욱더 좋을 것 같아요.",
    "essay_type": "글짓기",
    "essay_level": "2",
    "essay_len": 408,
    "essay_main_subject": "미래 도시에 대한 본인의 생각"
  }
}