{
  "paragraph": [
    {
      "paragraph_txt": "나에게 우주란 그 어디보다 제일 위험한 곳이라고 생각한다. #@문장구분# 우주는 그렇게 많은 사람들이 간 것은 아니다. #@문장구분# 그리고 우주에 완전히 정착하여 살아가는 사람은 없다. #@문장구분# 그렇기에 아무리 영리하고 몇 번 갔더라도 우주에서 일어날일은 아무도 예상할 수 없다. #@문장구분# 지구에서도 비슷하다. #@문장구분# 그러나 지구에서는 상상하지 못한 일이 일어난다고 한들 어떻게 하든 일은 풀릴수 있다. #@문장구분# 허나 우주는 그렇게 손을 쓸틈도 없이 사건 사고가 일어나도 이상하지 않는 곳이 우주다. #@문장구분# 그렇다고 멀리 할수도 없다.#@문장구분#  앞으로의 발전과 미래를 위해서라면 우주에 가서 조사하고도 해야 되기 때문에 무섭고 위험해 보여도 멀리할수 없다. #@문장구분# 마치 우주는 학교같다.#@문장구분#왜냐하면, 앞에서 언급했듯이 우리 인류는 살아가야 할 식량이 필요하듯이 과학기술이 필요하다. #@문장구분# 하지만, 여러 문제점이 생겨 인간에게 영향을 줄 수 있다. #@문장구분# 또한 일부는 텔레파시처럼 느낄 수 있지만 일부는 신의 명령처럼 느낄 수 있다. #@문장구분# 위를 바탕으로 과학기술은 장단점이 있어 무슨일이 일어날지 모른다.#@문장구분#  내·외부에서도 인간과의 영향이 있어서 나와 인류와의 관계에서 '과학기술'이라는 문명에서 필요한 도구인지 알 수 없다그 이유는 이 광활한 우주에 대해 나와 인류를 아는 것이 매우 빙산의 일각이라고 생각되기 때문이다. #@문장구분# 우리 지구에서는 분명히 작아보였던 별이 크기가 몇천배가 더 크다고 하니 미스테리하고 한번 알아보고 싶은 생각이든다. #@문장구분# 또한 우주는 진리의 대상일수도 있다.#@문장구분#  옛날 조선의 성리 학자들이 우주에 대해 연구한 전기는 다 의미가 있고 그만큼 가치가 있으니까 성리학이라는 학술이 나온 것 같다. #@문장구분# 그리고 우주는 우리에게 스트레스 해소의 공간이다. #@문장구분# 이상하게 들릴지 모르겠지만 스트레스 받고 답답하고 도무지 무엇을 해야하는지 모를 때 가끔 밖에 나와서 우주를 보고있으면 조금은 상쾌한 것 같기도하다.",
      "paragraph_len": 1290,
      "paragraph_id": "001"
    }
  ],
  "score": {
    "paragraph_score": [
      {
        "paragraph_scoreT": [
          3,
          3,
          2.7142856
        ],
        "paragraph_scoreT_detail": {
          "paragraph_scoreT_exp": [
            [
              3,
              3,
              3
            ],
            [
              3,
              3,
              3
            ],
            [
              2,
              3,
              3
            ]
          ]
        },
        "paragraph_scoreT_avg": 2.904762,
        "paragraph_id": "001"
      }
    ],
    "essay_scoreT": [
      28.5,
      27.5,
      25.52381
    ],
    "essay_scoreT_avg": 27.174604,
    "essay_scoreT_detail": {
      "essay_scoreT_org": [
        [
          3,
          3,
          3,
          3
        ],
        [
          3,
          3,
          3,
          3
        ],
        [
          2,
          2,
          3,
          3
        ]
      ],
      "essay_scoreT_cont": [
        [
          3,
          2,
          0,
          3
        ],
        [
          2,
          3,
          0,
          2
        ],
        [
          3,
          2,
          0,
          2
        ]
      ],
      "essay_scoreT_exp": [
        [
          3,
          3,
          3
        ],
        [
          3,
          3,
          3
        ],
        [
          2,
          3,
          3
        ]
      ]
    }
  },
  "student": {
    "date": "2021.12.23",
    "student_educated": true,
    "student_grade": "고등_2학년",
    "location": "063",
    "student_grade_group": "고등",
    "student_reading": 1
  },
  "rubric": {
    "essay_grade": "고등_2학년",
    "organization_weight": {
      "org_paragraph": 3,
      "org": 2,
      "org_essay": 3,
      "org_coherence": 2,
      "org_quantity": 1
    },
    "essay_type": "글짓기",
    "content_weight": {
      "con_clearance": 4,
      "con_novelty": 3,
      "con": 4,
      "con_prompt": 0,
      "con_description": 1
    },
    "essay_main_subject": "우주에 대한 나의 생각",
    "expression_weight": {
      "exp_style": 2,
      "exp_grammar": 2,
      "exp_vocab": 3,
      "exp": 4
    }
  },
  "correction": [],
  "info": {
    "essay_id": "ESSAY_79361",
    "essay_prompt": " 여러분은 '우주'라는 것에 대해 어떻게 생각하나요?\n\n 한 번도 생각해보지 않은 사람도 있을 것이고 평소에 우주의 신비에 대해 궁금해하는 사람도 있을 것 같아요.\n\n '우주'라는 공간은 아직 밝혀진 것도 많이 없고 많은 과학자에게 숙제 같은 곳이랍니다. 많은 SF영화에서는 저명한 우주학자들을 초빙하고 수많은 회의를 기반으로 다양한 해석을 통해 우주를 설명하고는 하지요. 인터스텔라나 마블유니버스의 스토리 처럼요!\n\n 여러분은 외계인이 있다고 생각하나요? 블랙홀이나 화이트홀은 어떻게 생각하나요? 우주여행이 가능하다고 생각하시나요? 아바타 같은 영화처럼 새로운 문명이 있다고 생각하나요? 진짜로 화성에 새로운 지구를 만들 수 있다고 생각하나요?\n\n 여러분은 이미 우주에 대한 영화나 책으로 많이 접해보았을 것 같아요. 그리고 10년, 20년 후의 우주에 대해 상상해 본 적이 있을 것 같아요. 우주에 대한 본인의 생각이나 미래의 일들을 자유롭게 작성해주세요.",
    "essay_type": "글짓기",
    "essay_level": "2",
    "essay_len": 912,
    "essay_main_subject": "우주에 대한 나의 생각"
  }
}