{
  "paragraph": [
    {
      "paragraph_txt": "우리 세계에는 많은 생물이 산다.#@문장구분#\n그중에서 수친중 가장 많은 비율을 차지하는 바다에 사는 동물중 내가 되고싶은 동물을 소개할려한다.#@문장구분#\n나는 돌고래가되고싶다.#@문장구분# 그이유는 자유롭기 때문이다. #@문장구분#난 학교에 갔다가 학원을 갔다가 친구집에서 놀거나 우리집에서 숙제하는 것 밖에 없다.#@문장구분#\n하지만 돌고래는 어디 묶여 있지않고 정말 자유롭게 살아갈 것 이다.#@문장구분#\n난 또 세계에 어딘가 숨겨져있는 아틀란티스를 찾는 모험을 하고싶다.#@문장구분#\n얼마나 흥미진진 할까 또 얼마나 자유로울까?#@문장구분# 그리고 돌고래늘 집단 행동을한다. #@문장구분#여러면이서 바다을 누비는 것 그것은 얼마나 멋있을까?#@문장구분# 이런 이유로난 돌고래가되고 싶다.",
      "paragraph_len": 519,
      "paragraph_id": "001"
    }
  ],
  "score": {
    "paragraph_score": [
      {
        "paragraph_scoreT": [
          2.5,
          2,
          2
        ],
        "paragraph_scoreT_detail": {
          "paragraph_scoreT_exp": [
            [
              2,
              3,
              0
            ],
            [
              2,
              2,
              0
            ],
            [
              2,
              2,
              0
            ]
          ]
        },
        "paragraph_scoreT_avg": 2.1666667,
        "paragraph_id": "001"
      }
    ],
    "essay_scoreT": [
      27.75,
      23.45,
      21.85
    ],
    "essay_scoreT_avg": 24.35,
    "essay_scoreT_detail": {
      "essay_scoreT_org": [
        [
          3,
          3,
          3,
          2
        ],
        [
          2,
          3,
          2,
          2
        ],
        [
          2,
          2,
          2,
          3
        ]
      ],
      "essay_scoreT_cont": [
        [
          3,
          3,
          0,
          3
        ],
        [
          3,
          3,
          0,
          2
        ],
        [
          3,
          2,
          0,
          2
        ]
      ],
      "essay_scoreT_exp": [
        [
          2,
          3,
          0
        ],
        [
          2,
          2,
          0
        ],
        [
          2,
          2,
          0
        ]
      ]
    }
  },
  "student": {
    "date": "2021.12.02",
    "student_educated": true,
    "student_grade": "초등_6학년",
    "location": "042",
    "student_grade_group": "초등",
    "student_reading": 2
  },
  "rubric": {
    "essay_grade": "초등_6학년",
    "organization_weight": {
      "org_paragraph": 1,
      "org": 2,
      "org_essay": 5,
      "org_coherence": 1,
      "org_quantity": 1
    },
    "essay_type": "글짓기",
    "content_weight": {
      "con_clearance": 4,
      "con_novelty": 4,
      "con": 4,
      "con_prompt": 0,
      "con_description": 2
    },
    "essay_main_subject": "바다 생물 이야기 짓기",
    "expression_weight": {
      "exp_style": 0,
      "exp_grammar": 3,
      "exp_vocab": 3,
      "exp": 4
    }
  },
  "correction": [
    {
      "sentence_corr_txt_grammar": "\n그중에서 수치 중 가장 많은 비율을 차지하는 바다에 사는 동물 중 내가 되고싶은 동물을 소개하려 한다.",
      "sentence_corr_reason": [
        "띄어쓰기"
      ],
      "sentence_id": "0002",
      "sentence_corr_type": [
        "문법"
      ],
      "sentence_corr_detail_type": [
        "맞춤법"
      ],
      "sentence_txt": "\n그중에서 <문법_맞춤법>수친중 </문법_맞춤법>가장 많은 비율을 차지하는 바다에 사는 동물중 내가 되고싶은 동물을 소개할려한다.",
      "sentence_corr_txt_styling": "",
      "paragraph_id": "001"
    },
    {
      "sentence_corr_txt_grammar": "\n나는 돌고래가 되고 싶다.",
      "sentence_corr_reason": [
        "띄어쓰기"
      ],
      "sentence_id": "0003",
      "sentence_corr_type": [
        "문법"
      ],
      "sentence_corr_detail_type": [
        "맞춤법"
      ],
      "sentence_txt": "\n나는 <문법_맞춤법>돌고래가되고싶다.</문법_맞춤법>",
      "sentence_corr_txt_styling": "",
      "paragraph_id": "001"
    },
    {
      "sentence_corr_txt_grammar": " 그 이유는 자유롭기 때문이다. ",
      "sentence_corr_reason": [
        "띄어쓰기"
      ],
      "sentence_id": "0004",
      "sentence_corr_type": [
        "문법"
      ],
      "sentence_corr_detail_type": [
        "맞춤법"
      ],
      "sentence_txt": " <문법_맞춤법>그이유는 </문법_맞춤법>자유롭기 때문이다. ",
      "sentence_corr_txt_styling": "",
      "paragraph_id": "001"
    },
    {
      "sentence_corr_txt_grammar": "난 학교에 갔다가 학원을 갔다가 친구집에서 놀거나 우리집에서 숙제하는 것밖에 없다.",
      "sentence_corr_reason": [
        "띄어쓰기"
      ],
      "sentence_id": "0005",
      "sentence_corr_type": [
        "문법"
      ],
      "sentence_corr_detail_type": [
        "맞춤법"
      ],
      "sentence_txt": "난 학교에 갔다가 학원을 갔다가 친구집에서 놀거나 우리집에서 숙제하는 <문법_맞춤법>것 밖에</문법_맞춤법> 없다.",
      "sentence_corr_txt_styling": "",
      "paragraph_id": "001"
    },
    {
      "sentence_corr_txt_grammar": "\n하지만 돌고래는 어디 묶여 있지않고 정말 자유롭게 살아갈 것이다.",
      "sentence_corr_reason": [
        "띄어쓰기"
      ],
      "sentence_id": "0006",
      "sentence_corr_type": [
        "문법"
      ],
      "sentence_corr_detail_type": [
        "맞춤법"
      ],
      "sentence_txt": "\n하지만 돌고래는 어디 묶여 있지않고 정말 자유롭게 살아갈 <문법_맞춤법>것 이다.</문법_맞춤법>",
      "sentence_corr_txt_styling": "",
      "paragraph_id": "001"
    },
    {
      "sentence_corr_txt_grammar": "\n난 또 세계에 어딘가 숨겨져 있는 아틀란티스를 찾는 모험을 하고 싶다.",
      "sentence_corr_reason": [
        "띄어쓰기"
      ],
      "sentence_id": "0007",
      "sentence_corr_type": [
        "문법"
      ],
      "sentence_corr_detail_type": [
        "맞춤법"
      ],
      "sentence_txt": "\n난 또 세계에 어딘가 <문법_맞춤법>숨겨져있는 </문법_맞춤법>아틀란티스를 찾는 모험을 하고싶다.",
      "sentence_corr_txt_styling": "",
      "paragraph_id": "001"
    },
    {
      "sentence_corr_txt_grammar": "\n얼마나 흥미진진할까 또 얼마나 자유로울까?",
      "sentence_corr_reason": [
        "띄어쓰기"
      ],
      "sentence_id": "0008",
      "sentence_corr_type": [
        "문법"
      ],
      "sentence_corr_detail_type": [
        "맞춤법"
      ],
      "sentence_txt": "\n얼마나 <문법_맞춤법>흥미진진 할까 </문법_맞춤법>또 얼마나 자유로울까?",
      "sentence_corr_txt_styling": "",
      "paragraph_id": "001"
    },
    {
      "sentence_corr_txt_grammar": " 그리고 돌고래는 집단 행동을 한다. ",
      "sentence_corr_reason": [
        ""
      ],
      "sentence_id": "0009",
      "sentence_corr_type": [
        "문법"
      ],
      "sentence_corr_detail_type": [
        "맞춤법"
      ],
      "sentence_txt": " 그리고 <문법_맞춤법>돌고래늘 </문법_맞춤법>집단 행동을한다. ",
      "sentence_corr_txt_styling": "",
      "paragraph_id": "001"
    },
    {
      "sentence_corr_txt_grammar": "여러 명이서 바다을 누비는 것 그것은 얼마나 멋있을까?",
      "sentence_corr_reason": [
        "띄어쓰기"
      ],
      "sentence_id": "0010",
      "sentence_corr_type": [
        "문법"
      ],
      "sentence_corr_detail_type": [
        "맞춤법"
      ],
      "sentence_txt": "<문법_맞춤법>여러면이서 </문법_맞춤법>바다을 누비는 것 그것은 얼마나 멋있을까?",
      "sentence_corr_txt_styling": "",
      "paragraph_id": "001"
    },
    {
      "sentence_corr_txt_grammar": " 이런 이유로 난 돌고래가 되고 싶다.",
      "sentence_corr_reason": [
        "띄어쓰기"
      ],
      "sentence_id": "0011",
      "sentence_corr_type": [
        "문법"
      ],
      "sentence_corr_detail_type": [
        "맞춤법"
      ],
      "sentence_txt": " 이런 <문법_맞춤법>이유로난 </문법_맞춤법>돌고래가되고 싶다.",
      "sentence_corr_txt_styling": "",
      "paragraph_id": "001"
    }
  ],
  "info": {
    "essay_id": "ESSAY_63225",
    "essay_prompt": " 바다는 지구 표면의 약 70%를 차지합니다. 그 속에는 무수한 생물이 살고 있는데 아직 밝혀지지 않은 종류도 많이 있습니다.\n\n 정말 넓고 신비로운 바다라는 곳에서 딱 일주일 동안 바다의 생물로 살아갈 기회가 주어진다면 여러분은 어떤 생물로 변신하고 싶으신가요?\n\n 원하는 생물을 정했다면 바다에서 어떤 모험을 하고 싶나요? 깊은 바다에 들어갈 수도 있고 아주 큰 고래가 되어 위험한 바다생물들을 도와줄 수도 있을 것 같아요.\n\n 관심 있는 바다 생물을 정하여 이유를 작성해주세요. 그리고 그 바다생물이 되어 바다를 모험하는 이야기를 상상하여 지어보세요.",
    "essay_type": "글짓기",
    "essay_level": "3",
    "essay_len": 319,
    "essay_main_subject": "바다 생물 이야기 짓기"
  }
}