{
  "paragraph": [
    {
      "paragraph_txt": "우주의 탄생과 멸망을 생각해본적이 있다. #@문장구분#우주가 창조될 때 원자가 만들어지면서 양성자 중성자가 원자핵을 이루고 이주변을 전자가 핵주변에서 어슬렁 거린다.#@문장구분# 원자핵의 강력에 의해 전자가 도망가지는 못하면서 전자기력에 의해 원자핵에 달라붙지도 않고 그렇게 원자의 주변에서 순간이동을 해가며 전자는 존재한다. #@문장구분#우리는 양성자를 플러스 전자는 마이너스로 표현을 한다.#@문장구분# 그런데 우주가 창조될 때 마이너스 양성자와 플러스 전자가 동시에 나왔다#@문장구분# 바로 지금 지구를 구성하는 물질의 반대 물질이 존재하는 것이다#@문장구분# 이것은 왜그런가#@문장구분# 바로 질량 보존의 법칙에 의해 우주에 존재하는 어떤물체도 남는 물질이 없이 무로 돌아갈수있어야 하기 때문이다. #@문장구분#이것은 디랙의 바다에서도 알수있듯이 반물질이라고 표현하는 양전자는 전자와 전자의 결합이 결국 마이너스와 마이너스로 플러스가 되는 상황을 디랙이 상상하고 실험으로 옮긴 것이 실제 플러스 전자를 띄는 반물질이 생성되므로 플러스와마이너스의 존재는 0을 만들므로 결국 무로 돌아가게 된다. #@문장구분#그런데 이때 이들이 상쇄되어 사라질 때 에너지를 내게 되고 입자가 사라지면서 내게되는 물질에서 감마선이 나오게 되는데 인간은 가시광선을 관찰할수있을뿐 감마선은 관찰을 할 수가 없고 이 감마선은 사람의 몸을 투과하고 벽을 투과하고 지구상의 모든 물질을 투과하고 눈에 보이지도 않느 선이다 #@문장구분#바로 이 감마선의 에너지는 E=MC2으로 물질을 생성하는데 그이후엔 전혀 새로운 물질로 감마선의 물질과 에너지를 가진 존재들이 빅뱅때처럼 재 창조가 되면서 기존의 생물들은 모두 죽고 감마선을 내뿜으면서살아가는 새로운 존재들이 등장하면서  새로운 생명체가 우주의 주인이 된다.",
      "paragraph_len": 1017,
      "paragraph_id": "001"
    }
  ],
  "score": {
    "paragraph_score": [
      {
        "paragraph_scoreT": [
          2.7142856,
          3,
          3
        ],
        "paragraph_scoreT_detail": {
          "paragraph_scoreT_exp": [
            [
              2,
              3,
              3
            ],
            [
              3,
              3,
              3
            ],
            [
              3,
              3,
              3
            ]
          ]
        },
        "paragraph_scoreT_avg": 2.904762,
        "paragraph_id": "001"
      }
    ],
    "essay_scoreT": [
      24.857143,
      26,
      26
    ],
    "essay_scoreT_avg": 25.61905,
    "essay_scoreT_detail": {
      "essay_scoreT_org": [
        [
          3,
          3,
          3,
          3
        ],
        [
          3,
          3,
          3,
          3
        ],
        [
          3,
          3,
          3,
          3
        ]
      ],
      "essay_scoreT_cont": [
        [
          2,
          2,
          0,
          2
        ],
        [
          2,
          2,
          0,
          2
        ],
        [
          2,
          2,
          0,
          2
        ]
      ],
      "essay_scoreT_exp": [
        [
          2,
          3,
          3
        ],
        [
          3,
          3,
          3
        ],
        [
          3,
          3,
          3
        ]
      ]
    }
  },
  "student": {
    "date": "2021.12.17",
    "student_educated": true,
    "student_grade": "고등_2학년",
    "location": "044",
    "student_grade_group": "고등",
    "student_reading": 2
  },
  "rubric": {
    "essay_grade": "고등_2학년",
    "organization_weight": {
      "org_paragraph": 3,
      "org": 2,
      "org_essay": 3,
      "org_coherence": 2,
      "org_quantity": 1
    },
    "essay_type": "글짓기",
    "content_weight": {
      "con_clearance": 4,
      "con_novelty": 3,
      "con": 4,
      "con_prompt": 0,
      "con_description": 1
    },
    "essay_main_subject": "우주에 대한 나의 생각",
    "expression_weight": {
      "exp_style": 2,
      "exp_grammar": 2,
      "exp_vocab": 3,
      "exp": 4
    }
  },
  "correction": [],
  "info": {
    "essay_id": "ESSAY_66977",
    "essay_prompt": " 여러분은 '우주'라는 것에 대해 어떻게 생각하나요?\n\n 한 번도 생각해보지 않은 사람도 있을 것이고 평소에 우주의 신비에 대해 궁금해하는 사람도 있을 것 같아요.\n\n '우주'라는 공간은 아직 밝혀진 것도 많이 없고 많은 과학자에게 숙제 같은 곳이랍니다. 많은 SF영화에서는 저명한 우주학자들을 초빙하고 수많은 회의를 기반으로 다양한 해석을 통해 우주를 설명하고는 하지요. 인터스텔라나 마블유니버스의 스토리 처럼요!\n\n 여러분은 외계인이 있다고 생각하나요? 블랙홀이나 화이트홀은 어떻게 생각하나요? 우주여행이 가능하다고 생각하시나요? 아바타 같은 영화처럼 새로운 문명이 있다고 생각하나요? 진짜로 화성에 새로운 지구를 만들 수 있다고 생각하나요?\n\n 여러분은 이미 우주에 대한 영화나 책으로 많이 접해보았을 것 같아요. 그리고 10년, 20년 후의 우주에 대해 상상해 본 적이 있을 것 같아요. 우주에 대한 본인의 생각이나 미래의 일들을 자유롭게 작성해주세요.",
    "essay_type": "글짓기",
    "essay_level": "2",
    "essay_len": 820,
    "essay_main_subject": "우주에 대한 나의 생각"
  }
}