{
  "paragraph": [
    {
      "paragraph_txt": "내 미래의 모습을 생각하면 나는 항상 웃으면서 나의 미래에 대해 생각을 할 때마다 행복했던 것 같다. #@문장구분#왜냐하면 무수하게 많은 상상들을 할 수 있기 때문이다.#@문장구분# 내가 미래의 배우자와 살아가고 있는 상황을 상상하고 있다거나 꿈을 이룬 나의 모습을 상상하며 내가 미래를 바꿀 수도 있겠다는 생각도 했었다. #@문장구분#나의 꿈은 위대한 간호사다. #@문장구분#엄마는 내가 간호사의 꿈을 꾸니 그런 말을 하였다.#@문장구분# \"돈 잘 버는 의사와 만나서 결혼을 하라\"라고 했었다. #@문장구분#하지만 나는 돈이 다가 아니라고 생각한다.#@문장구분# 나는 내가 좋아하는 사람과 결혼을 하고 싶다. #@문장구분#나의 집안이 어떻더라도 따지지 않고 나의 모습이 어떻더라도 사랑해주고 이뻐해 주는 사람과 결혼할 것이다. #@문장구분#그래서 10년 뒤의 모습은 내가 사랑하는 사람과 열심히 사랑하고 있을 것이고 20년 뒤에는 내가 사랑하는 사람과 가정을 꾸미고 열심히 일을 하고 있을 것이다.#@문장구분# 30년 뒤에는 완벽하게 가정을 꾸려 아이들도 거의 다 커가고 돈을 많이 모아서 미래의 배우자와 열심히 여행을 다닐 것을 계획으로 삼고 있다. #@문장구분#그렇게 행복한 나날들을 꿈꾸면서 열심히 미래를 꿈꾸며 성장할 것이다.#@문장구분# 커서 간호사가 꼭 되어 있으면 좋겠다.#@문장구분#",
      "paragraph_len": 840,
      "paragraph_id": "001"
    }
  ],
  "score": {
    "paragraph_score": [
      {
        "paragraph_scoreT": [
          3,
          2.8333333,
          2.5
        ],
        "paragraph_scoreT_detail": {
          "paragraph_scoreT_exp": [
            [
              3,
              3,
              3
            ],
            [
              3,
              3,
              2
            ],
            [
              2,
              3,
              2
            ]
          ]
        },
        "paragraph_scoreT_avg": 2.7777777,
        "paragraph_id": "001"
      }
    ],
    "essay_scoreT": [
      30,
      26.222221,
      23.61111
    ],
    "essay_scoreT_avg": 26.611109,
    "essay_scoreT_detail": {
      "essay_scoreT_org": [
        [
          3,
          3,
          3,
          3
        ],
        [
          2,
          3,
          3,
          2
        ],
        [
          3,
          2,
          2,
          3
        ]
      ],
      "essay_scoreT_cont": [
        [
          3,
          3,
          0,
          3
        ],
        [
          3,
          2,
          0,
          2
        ],
        [
          2,
          2,
          0,
          3
        ]
      ],
      "essay_scoreT_exp": [
        [
          3,
          3,
          3
        ],
        [
          3,
          3,
          2
        ],
        [
          2,
          3,
          2
        ]
      ]
    }
  },
  "student": {
    "date": "2021.12.11",
    "student_educated": true,
    "student_grade": "중등_2학년",
    "location": "054",
    "student_grade_group": "중등",
    "student_reading": 3
  },
  "rubric": {
    "essay_grade": "중등_2학년",
    "organization_weight": {
      "org_paragraph": 2,
      "org": 2,
      "org_essay": 4,
      "org_coherence": 2,
      "org_quantity": 1
    },
    "essay_type": "글짓기",
    "content_weight": {
      "con_clearance": 4,
      "con_novelty": 3,
      "con": 4,
      "con_prompt": 0,
      "con_description": 1
    },
    "essay_main_subject": "미래의 나의 모습",
    "expression_weight": {
      "exp_style": 1,
      "exp_grammar": 2,
      "exp_vocab": 3,
      "exp": 4
    }
  },
  "correction": [],
  "info": {
    "essay_id": "ESSAY_67934",
    "essay_prompt": " 우리는 모두 미래의 나를 한 번씩 상상해보곤 합니다. 유명한 사람이 돼서 많은 사람과 소통하는 상상, 훌륭한 의사가 돼서 많은 사람을 살리는 상상 등 어떤 사람이 되고 싶다는 미래를 생각하지요.\n\n 여러분은 미래의 나를 상상해보신 적이 있으신가요? 10년 뒤, 20년 뒤, 30년 뒤에 여러분은 어떤 일을 하고 어떤 가치관을 가지고 살아가고 있을까요?\n\n 나의 10년 뒤, 20년 뒤, 30년 뒷모습을 각각 상상해보고 어떤 일을 하고 있을지, 그러한 모습을 갖추기 위해 어떤 노력을 하였을지 작성해보세요.",
    "essay_type": "글짓기",
    "essay_level": "2",
    "essay_len": 580,
    "essay_main_subject": "미래의 나의 모습"
  }
}